yan/__init__.py
yan/infer_util.py
yan/model/__init__.py
yan/model/yan_brain.py
yan/model/yan_configuration.py
yan/pyarmor_runtime_000000/__init__.py
yan/pyarmor_runtime_000000/pyarmor_runtime.so
yan/tokenizer/__init__.py
yan/tokenizer/yan_tokenization.py
yan_infer_test1-0.0.18.dist-info/LICENSE
yan_infer_test1-0.0.18.dist-info/METADATA
yan_infer_test1-0.0.18.dist-info/WHEEL
yan_infer_test1-0.0.18.dist-info/top_level.txt
yan_infer_test1-0.0.18.dist-info/RECORD
